cli/__init__.py
cli/download_cmd.py
cli/main.py
cli/root.py
config/__init__.py
config/loader.py
data/bill_profile.py
factory/downloader_factory.py
factory/email_factory.py
factory/provider_factory.py
package/__init__.py
package/downfile.py
strategy/downloader/__init__.py
strategy/downloader/attchment.py
strategy/downloader/provider.py
strategy/email/__init__.py
strategy/email/email_provider.py
strategy/email/gmail.py
strategy/provider/ali_provider.py
strategy/provider/provider.py
download_flow_enmu-0.1.0.dist-info/METADATA
download_flow_enmu-0.1.0.dist-info/WHEEL
download_flow_enmu-0.1.0.dist-info/entry_points.txt
download_flow_enmu-0.1.0.dist-info/top_level.txt
download_flow_enmu-0.1.0.dist-info/RECORD
