Metadata-Version: 2.4
Name: download-flow-enmu
Version: 0.1.0
Summary: A task flow management tool for syncing todo files with taskwarrior
Author-email: Your Name <your.email@example.com>
Classifier: Development Status :: 3 - Alpha
Classifier: Intended Audience :: Developers
Classifier: Programming Language :: Python :: 3
Classifier: Programming Language :: Python :: 3.10
Classifier: Programming Language :: Python :: 3.11
Classifier: Programming Language :: Python :: 3.12
Requires-Python: >=3.10
Requires-Dist: typer>=0.9.0
Requires-Dist: pydantic>=2.0.0
Requires-Dist: imap_tools
Requires-Dist: python-dotenv>=1.0.0
Provides-Extra: dev
Requires-Dist: pytest>=7.0.0; extra == "dev"
